upload_path_pyramid/__init__.py
upload_path_pyramid-0.1.0.dist-info/LICENSE
upload_path_pyramid-0.1.0.dist-info/WHEEL
upload_path_pyramid-0.1.0.dist-info/METADATA
upload_path_pyramid-0.1.0.dist-info/RECORD
